tagme/__init__.py
tagme-0.1.3.dist-info/DESCRIPTION.rst
tagme-0.1.3.dist-info/METADATA
tagme-0.1.3.dist-info/RECORD
tagme-0.1.3.dist-info/WHEEL
tagme-0.1.3.dist-info/metadata.json
tagme-0.1.3.dist-info/top_level.txt
