Metadata-Version: 1.1
Name: tagme
Version: 0.1.3
Summary: Official TagMe API wrapper for Python
Home-page: https://github.com/marcocor/tagme-python
Author: Marco Cornolti
Author-email: cornolti@di.unipi.it
License: Apache
Keywords: entity-linking nlp tagme api
Platform: UNKNOWN
Classifier: Development Status :: 4 - Beta
Classifier: Intended Audience :: Developers
Classifier: Intended Audience :: Information Technology
Classifier: Intended Audience :: Science/Research
Classifier: License :: OSI Approved :: Apache Software License
Classifier: Operating System :: OS Independent
Classifier: Topic :: Scientific/Engineering :: Information Analysis
Classifier: Topic :: Software Development :: Libraries :: Python Modules
Classifier: Topic :: Text Processing :: Linguistic
Classifier: Programming Language :: Python :: 2
Classifier: Programming Language :: Python :: 2.7
Classifier: Programming Language :: Python :: 3
Classifier: Programming Language :: Python :: 3.5
